INSTALL.rst
LICENSE
MANIFEST.in
README.rst
VERSION
requirements.txt
setup.py
src/boxed/__init__.py
src/boxed/__main__.py
src/boxed/__meta__.py
src/boxed/core.py
src/boxed/errors.py
src/boxed/pinteract.py
src/boxed/runners.py
src/boxed.egg-info/PKG-INFO
src/boxed.egg-info/SOURCES.txt
src/boxed.egg-info/dependency_links.txt
src/boxed.egg-info/entry_points.txt
src/boxed.egg-info/not-zip-safe
src/boxed.egg-info/requires.txt
src/boxed.egg-info/top_level.txt
src/boxed/coverage/__init__.py
src/boxed/coverage/__main__.py
src/boxed/jsonbox/__init__.py
src/boxed/jsonbox/__main__.py
src/boxed/picklebox/__init__.py
src/boxed/picklebox/__main__.py
src/boxed/tests/__init__.py
src/boxed/tests/__main__.py
src/boxed/tests/test_boxed.py
src/boxed/tests/test_core.py
src/boxed/tests/test_documentation.py
src/boxed/tests/test_jsonbox.py
src/boxed/tests/test_pinteract.py